releasely/__init__.py
releasely/__main__.py
releasely/compat.py
releasely/config.py
releasely/git.py
releasely/release_info.py
releasely/version.py
releasely/tasks/__init__.py
releasely/tasks/check.py
releasely/tasks/prepare_release.py
releasely/tasks/release_notes.py
releasely-1.1.0.dist-info/METADATA
releasely-1.1.0.dist-info/RECORD
releasely-1.1.0.dist-info/WHEEL
releasely-1.1.0.dist-info/entry_points.txt
releasely-1.1.0.dist-info/top_level.txt
